geneval/__init__.py
geneval/cli.py
geneval/config.py
geneval/core.py
geneval/data/__init__.py
geneval/data/gene_expression_datamodule.py
geneval/data/loader.py
geneval/evaluator.py
geneval/evaluators/__init__.py
geneval/evaluators/base_evaluator.py
geneval/evaluators/gene_expression_evaluator.py
geneval/metrics/__init__.py
geneval/metrics/base_metric.py
geneval/metrics/correlation.py
geneval/metrics/distances.py
geneval/metrics/metrics.py
geneval/models/__init__.py
geneval/models/base_model.py
geneval/results.py
geneval/testing.py
geneval/utils/__init__.py
geneval/utils/io.py
geneval/utils/preprocessing.py
geneval/visualization/__init__.py
geneval/visualization/plots.py
geneval/visualization/visualizer.py
gengeneeval-0.1.1.dist-info/METADATA
gengeneeval-0.1.1.dist-info/WHEEL
gengeneeval-0.1.1.dist-info/entry_points.txt
gengeneeval-0.1.1.dist-info/licenses/LICENSE
gengeneeval-0.1.1.dist-info/RECORD
