Metadata-Version: 2.4
Name: gengeneeval
Version: 0.1.1
Summary: Comprehensive evaluation of generated gene expression data. Computes metrics between real and generated datasets with support for condition matching, train/test splits, and publication-quality visualizations.
License: MIT
License-File: LICENSE
Keywords: gene expression,evaluation,metrics,single-cell,generative models,benchmarking
Author: GenEval Team
Author-email: geneval@example.com
Requires-Python: >=3.8,<4.0
Classifier: Development Status :: 4 - Beta
Classifier: Intended Audience :: Science/Research
Classifier: License :: OSI Approved :: MIT License
Classifier: Programming Language :: Python :: 3
Classifier: Programming Language :: Python :: 3.8
Classifier: Programming Language :: Python :: 3.9
Classifier: Programming Language :: Python :: 3.10
Classifier: Programming Language :: Python :: 3.11
Classifier: Programming Language :: Python :: 3.12
Classifier: Programming Language :: Python :: 3.13
Classifier: Programming Language :: Python :: 3.14
Classifier: Topic :: Scientific/Engineering :: Bio-Informatics
Provides-Extra: full
Provides-Extra: gpu
Requires-Dist: anndata (>=0.8.0)
Requires-Dist: geomloss (>=0.2.1) ; extra == "full" or extra == "gpu"
Requires-Dist: matplotlib (>=3.5.0)
Requires-Dist: numpy (>=1.21.0)
Requires-Dist: pandas (>=1.3.0)
Requires-Dist: pykeops (>=1.4.0) ; extra == "full" or extra == "gpu"
Requires-Dist: scanpy (>=1.9.0)
Requires-Dist: scipy (>=1.7.0)
Requires-Dist: seaborn (>=0.11.0)
Requires-Dist: torch (>=1.9.0)
Requires-Dist: umap-learn (>=0.5.0) ; extra == "full"
Project-URL: Homepage, https://github.com/AndreaRubbi/GenGeneEval
Project-URL: Repository, https://github.com/AndreaRubbi/GenGeneEval
